{
  "trainers": [
    {
      "id": "t1",
      "roster": [
        "p1",
        "p2"
      ],
      "email": "trainer@trainer.com",
      "name": "t-dog",
      "age": "45"
    }
  ],
  "pokemon": [
    {
      "id": "p1",
      "trainerId": "t1",
      "order": 1,
      "nickname": "patches",
      "img": "",
      "description": "its a pokemon",
      "name": "psyduck"
    },
    {
      "id": "p2",
      "trainerId": "t1",
      "order": 1,
      "nickname": "charcole",
      "img": "",
      "description": "its a pokemon",
      "name": "charmander"
    }
  ],
  "pokedex": [
    {
      "id": "102",
      "img": "",
      "description": "its a pokemon",
      "name": "psyduck"
    },
    {
      "id": "1",
      "img": "",
      "description": "its a pokemon",
      "name": "charmander"
    }
  ]
}